kafka_connect/__init__.py
kafka_connect_python-0.0.3.dist-info/LICENSE.txt
kafka_connect_python-0.0.3.dist-info/METADATA
kafka_connect_python-0.0.3.dist-info/RECORD
kafka_connect_python-0.0.3.dist-info/WHEEL
kafka_connect_python-0.0.3.dist-info/top_level.txt
